beats/__init__.py
beats/cli.py
beats/constants.py
beats/filtering.py
beats/shared_types.py
beats/estimators/__init__.py
beats/estimators/api.py
beats/estimators/librosa.py
beats/estimators/transformed.py
beats/estimators/trivial.py
beats/estimators/utils.py
beats_swing-0.1.5.dist-info/METADATA
beats_swing-0.1.5.dist-info/WHEEL
beats_swing-0.1.5.dist-info/entry_points.txt
beats_swing-0.1.5.dist-info/licenses/LICENSE.txt
beats_swing-0.1.5.dist-info/RECORD
