Metadata-Version: 2.3
Name: beats_swing
Version: 0.1.5
Summary: Determine the tempo of an mp3 song. Tweaked for swing music.
Project-URL: repository, https://github.com/elvijs/beats
Project-URL: homepage, https://github.com/elvijs/beats
Project-URL: issues, https://github.com/elvijs/beats/issues
Author-email: Elvijs Sarkans <elvijs.sarkans@gmail.com>
License-File: LICENSE.txt
Classifier: License :: OSI Approved :: MIT License
Classifier: Operating System :: OS Independent
Classifier: Programming Language :: Python :: 3
Requires-Python: >=3.11
Requires-Dist: librosa<1,>=0.10.2
